<?xml version="1.0" encoding="UTF-8"?>
<beans xmlns="http://www.springframework.org/schema/beans"
	xmlns:context="http://www.springframework.org/schema/context" xmlns:p="http://www.springframework.org/schema/p"
	xmlns:dubbo="http://code.alibabatech.com/schema/dubbo"
	xmlns:xsi="http://www.w3.org/2001/XMLSchema-instance"
	xsi:schemaLocation="http://www.springframework.org/schema/beans http://www.springframework.org/schema/beans/spring-beans-4.0.xsd
	http://www.springframework.org/schema/context http://www.springframework.org/schema/context/spring-context-4.3.xsd
	http://code.alibabatech.com/schema/dubbo http://code.alibabatech.com/schema/dubbo/dubbo.xsd">
    	<!-- 加载配置文件 -->
	<context:property-placeholder location="classpath:properties/*.properties" />
    
	
    <!-- 提供方应用信息，用于计算依赖关系 -->  
    <dubbo:application name="${dubbo.application.name}" />  
    
    <!-- 注册中心暴露服务地址 -->  
   <dubbo:registry protocol="${dubbo.registry.protocol}" address="${dubbo.registry.address}" />
   
   <dubbo:protocol name="${dubbo.protocol.name}" port="${dubbo.protocol.port}"/>
   <!-- 启动时找不到服务提供者忽略 -->
   <dubbo:consumer check="false"/>

    <!-- 声明需要暴露的服务接口 -->
    <!-- sso系统接口 -->
    <!-- 用户接口 -->
    <dubbo:reference id="userServerFacade" timeout="3000" interface="com.blogforum.sso.facade.user.UserServerFacade"/>
    <!-- session相关接口 -->
    <dubbo:reference id="sessionServerFacade" timeout="3000" interface="com.blogforum.sso.facade.session.SessionServerFacade"/>
    <!-- 搜索相关接口 -->
    <dubbo:reference id="solrServiceFacade" timeout="3000" interface="com.blogforum.search.facade.service.SolrServiceFacade"/>
    
</beans>